nonebot_plugin_maimaidx/__init__.py
nonebot_plugin_maimaidx/config.py
nonebot_plugin_maimaidx/maimaidxhelp.png
nonebot_plugin_maimaidx/command/__init__.py
nonebot_plugin_maimaidx/command/mai_alias.py
nonebot_plugin_maimaidx/command/mai_base.py
nonebot_plugin_maimaidx/command/mai_guess.py
nonebot_plugin_maimaidx/command/mai_score.py
nonebot_plugin_maimaidx/command/mai_search.py
nonebot_plugin_maimaidx/command/mai_table.py
nonebot_plugin_maimaidx/libraries/image.py
nonebot_plugin_maimaidx/libraries/maimaidx_api_data.py
nonebot_plugin_maimaidx/libraries/maimaidx_best_50.py
nonebot_plugin_maimaidx/libraries/maimaidx_error.py
nonebot_plugin_maimaidx/libraries/maimaidx_model.py
nonebot_plugin_maimaidx/libraries/maimaidx_music.py
nonebot_plugin_maimaidx/libraries/maimaidx_music_info.py
nonebot_plugin_maimaidx/libraries/maimaidx_player_score.py
nonebot_plugin_maimaidx/libraries/maimaidx_update_plate.py
nonebot_plugin_maimaidx/libraries/tool.py
nonebot_plugin_maimaidx-2.1.11.dist-info/licenses/LICENSE
nonebot_plugin_maimaidx-2.1.11.dist-info/METADATA
nonebot_plugin_maimaidx-2.1.11.dist-info/WHEEL
nonebot_plugin_maimaidx-2.1.11.dist-info/top_level.txt
nonebot_plugin_maimaidx-2.1.11.dist-info/RECORD
