Metadata-Version: 2.4
Name: nonebot-plugin-maimaidx
Version: 2.1.11
Summary: maimaidx plugin for nonebot2
Author-email: Yuri-YuzuChaN <806235364@qq.com>
License-Expression: MIT
Project-URL: Homepage, https://github.com/Yuri-YuzuChaN/nonebot-plugin-maimaidx
Project-URL: Bug Tracker, https://github.com/Yuri-YuzuChaN/nonebot-plugin-maimaidx/issues
Classifier: Programming Language :: Python :: 3
Classifier: Operating System :: OS Independent
Requires-Python: >=3.9
License-File: LICENSE
Requires-Dist: nonebot2<3.0.0,>=2.0.0
Requires-Dist: nonebot-adapter-onebot<3.0.0,>=2.2.2
Requires-Dist: nonebot-plugin-apscheduler<1.0.0,>=0.3.0
Requires-Dist: aiofiles<25.0.0,>=23.2.1
Requires-Dist: httpx<1.0.0,>=0.23.1
Requires-Dist: pydantic<3.0.0,>=2.0.0
Requires-Dist: pyecharts<3.0.0,>=2.0.0
Requires-Dist: playwright>=1.52.0
Requires-Dist: httpx-ws<1.0.0,>=0.7.2
Requires-Dist: pillow<11.0.0,>=10.0.0; python_version < "3.13"
Requires-Dist: pillow<12.0.0,>=11.0.0; python_version >= "3.13"
Requires-Dist: numpy==1.26.0; python_version < "3.10"
Requires-Dist: numpy<3.0.0,>=2.0.0; python_version >= "3.10"
Dynamic: license-file
